[{"iasAuditEntry": {"iasAuditHeader": {"iasAuditRecordDate": "1975-10-10 23:12:54", "iasClientIdentifier": "Alexander", "iasApplicationIdentifier": "Ignix", "iasAuditType": "AUTH", "iasAuditSessionID": "iasAuditSessionID10", "iasOrganisationalUnit": "Medina, Warner and Cunningham", "iasAuditID": "10", "iasAuditMetadata": {"iasMetaData": "1984-08-27 06:07:42", "iasMetaType": "iasMetaType10", "iasMetaSecurityRole": "Admin Only", "iasMetaSecurityViewer": {"iasAuditRecordViewer": {"unauthorisedAuditViewer": "Mike", "authorisedAuditViewer": "Andrew"}}, "iasMetaClassification": {"iasDataClassification": {"iasAuditRecordClassifaction": "OFFICIAL"}}, "iasMetaDataPayload": "user : John", "iasMetaRetension": "iasMetaRetension10"}}}}]
